{
	"create_time":	1603096305160,
	"events":	[{
			"example_speech_template":	"<%设备名-灯类%><%房间名%><%全部%>",
			"request_slots":	[{
					"value_expression":	"%设备名-灯类%",
					"name":	"%设备名-灯类%",
					"value_source":	"svd",
					"example_value":	"%设备名-灯类%"
				}, {
					"value_expression":	"%房间名%",
					"name":	"%房间名%",
					"value_source":	"svd",
					"example_value":	"%房间名%"
				}, {
					"value_expression":	"%全部%",
					"name":	"%全部%",
					"value_source":	"svd",
					"example_value":	"%全部%"
				}],
			"intent_prefix":	"控客全屋智能语音面板_用户_语义补全",
			"id":	1,
			"type":	"u2a_speech"
		}, {
			"request_slots":	[],
			"intent_prefix":	"控客全屋智能语音面板_动作_询问及补全信息_AE4E918A14C0BFCD5E4AA388D5001228",
			"response_slots":	[{
					"value_expression":	"成功",
					"name":	"状态",
					"value_source":	"const"
				}],
			"type":	"a2s"
		}, {
			"request_slots":	[],
			"intent_prefix":	"release_turn_0",
			"type":	"a2u_api_call"
		}, {
			"example_speech_template":	"<%参数名-温度%><%动词-降低到%><%设定值-极值最低_极值最冷_极值最小%>",
			"request_slots":	[{
					"value_expression":	"%参数名-温度%",
					"value_source":	"svd",
					"name":	"%参数名-温度%",
					"example_value":	"%参数名-温度%"
				}, {
					"value_expression":	"%动词-降低到%",
					"value_source":	"svd",
					"name":	"%动词-降低到%",
					"example_value":	"%动词-降低到%"
				}, {
					"value_expression":	"%设定值-极值最低_极值最冷_极值最小%",
					"value_source":	"svd",
					"name":	"%设定值-极值最低_极值最冷_极值最小%",
					"example_value":	"%设定值-极值最低_极值最冷_极值最小%"
				}],
			"intent_prefix":	"控客全屋智能语音面板_用户_运行控制_温度调到",
			"id":	11,
			"type":	"u2a_speech"
		}, {
			"request_slots":	[{
					"value_expression":	"11/%设定值-极值最低_极值最冷_极值最小%",
					"name":	"%设定值%",
					"value_source":	"context"
				}, {
					"value_expression":	"1/%房间名%",
					"name":	"%房间名%",
					"value_source":	"context"
				}],
			"intent_prefix":	"控客全屋智能语音面板_动作_运行控制_温度调到",
			"response_slots":	[{
					"value_expression":	"成功",
					"name":	"状态",
					"value_source":	"const"
				}],
			"type":	"a2s"
		}, {
			"request_slots":	[],
			"intent_prefix":	"release_turn",
			"type":	"a2u_api_call"
		}],
	"labels":	[]
}
